es51922_view.py
setup.py
es51922_viewer/__init__.py
es51922_viewer/comm.py
es51922_viewer/meter.py
es51922_viewer/parser.py
es51922_viewer/settings.py
es51922_viewer/ui.py
es51922_viewer/utils.py
es51922_viewer/version.py
es51922_viewer/widget_lcd.py
es51922_viewer/widget_led.py
es51922_viewer/widget_plot.py
es51922_viewer/window_main.py
es51922_viewer.egg-info/PKG-INFO
es51922_viewer.egg-info/SOURCES.txt
es51922_viewer.egg-info/dependency_links.txt
es51922_viewer.egg-info/requires.txt
es51922_viewer.egg-info/top_level.txt
es51922_viewer/gui/__init__.py
es51922_viewer/gui/__init__.pyc
es51922_viewer/gui/clear.png
es51922_viewer/gui/mainwindow.ui
es51922_viewer/gui/record.png