Metadata-Version: 1.1
Name: es51922-viewer
Version: 0.1.1
Summary: Monitor ES51022 based multimeters.
Home-page: https://eartoearoak.com/software/es51922-viewer
Author: Al Brown
Author-email: al [at] eartoearok.com
License: GPLv3
Keywords: multimeter dmm ES51022 ut61
Platform: UNKNOWN
Classifier: Development Status :: 4 - Beta
Classifier: License :: OSI Approved :: GNU General Public License v3 (GPLv3)
Classifier: Operating System :: MacOS :: MacOS X
Classifier: Operating System :: Microsoft :: Windows
Classifier: Operating System :: POSIX :: Linux
Classifier: Programming Language :: Python :: 2.7
Classifier: Topic :: Scientific/Engineering
Classifier: Topic :: Scientific/Engineering :: Visualization
